{
  "project_info": {
    "project_number": "306160410053",
    "project_id": "customtwiliophone",
    "storage_bucket": "customtwiliophone.appspot.com"
  },
  "client": [
    {
      "client_info": {
        "mobilesdk_app_id": "1:306160410053:android:efb5477ac98e1efb14ffac",
        "android_client_info": {
          "package_name": "com.customtwiliophone"
        }
      },
      "oauth_client": [
        {
          "client_id": "306160410053-jgpb761ru831hulgcf341uku542h1gs2.apps.googleusercontent.com",
          "client_type": 3
        }
      ],
      "api_key": [
        {
          "current_key": "AIzaSyDccB2AJxIs2dWCBVir1BOhL5dWK5Xbc4M"
        }
      ],
      "services": {
        "appinvite_service": {
          "other_platform_oauth_client": [
            {
              "client_id": "306160410053-jgpb761ru831hulgcf341uku542h1gs2.apps.googleusercontent.com",
              "client_type": 3
            }
          ]
        }
      }
    }
  ],
  "configuration_version": "1"
}